heisenbridge/__init__.py
heisenbridge/__main__.py
heisenbridge/appservice.py
heisenbridge/channel_room.py
heisenbridge/command_parse.py
heisenbridge/control_room.py
heisenbridge/event_queue.py
heisenbridge/hidden_room.py
heisenbridge/identd.py
heisenbridge/irc.py
heisenbridge/network_room.py
heisenbridge/parser.py
heisenbridge/plumbed_room.py
heisenbridge/private_room.py
heisenbridge/room.py
heisenbridge/space_room.py
heisenbridge/version.py
heisenbridge/version.txt
heisenbridge/websocket.py
heisenbridge-1.15.3.dist-info/licenses/LICENSE
heisenbridge-1.15.3.dist-info/METADATA
heisenbridge-1.15.3.dist-info/WHEEL
heisenbridge-1.15.3.dist-info/entry_points.txt
heisenbridge-1.15.3.dist-info/top_level.txt
heisenbridge-1.15.3.dist-info/RECORD
