Metadata-Version: 2.4
Name: heisenbridge
Version: 1.15.3
Summary: a bouncer-style Matrix IRC bridge
Home-page: https://github.com/hifi/heisenbridge
Author: Toni Spets (hifi)
Author-email: toni.spets@iki.fi
License: MIT license
Requires-Python: >=3.10
License-File: LICENSE
Requires-Dist: irc<20.4,>=19.0.0
Requires-Dist: ruamel.yaml<0.19,>=0.15.35
Requires-Dist: mautrix<0.21,>=0.20.5
Requires-Dist: python-socks[asyncio]>=1.2.4
Requires-Dist: aiohttp<4.0.0,>=3.8.0
Provides-Extra: dev
Requires-Dist: mypy; extra == "dev"
Requires-Dist: flake8; extra == "dev"
Requires-Dist: black>=22.3.0; extra == "dev"
Requires-Dist: reorder-python-imports; extra == "dev"
Requires-Dist: pre-commit; extra == "dev"
Requires-Dist: setuptools; extra == "dev"
Provides-Extra: test
Requires-Dist: pytest; extra == "test"
Dynamic: license-file
